runtime_info0/__init__.py
runtime_info0/pytest_runtime_info.py
runtime_info-0.15.10.dist-info/LICENSE
runtime_info-0.15.10.dist-info/METADATA
runtime_info-0.15.10.dist-info/WHEEL
runtime_info-0.15.10.dist-info/entry_points.txt
runtime_info-0.15.10.dist-info/top_level.txt
runtime_info-0.15.10.dist-info/RECORD
